MADRLmine/__init__.py
MADRLmine/Hybrid_A_starPlanner_RS/__init__.py
MADRLmine/Hybrid_A_starPlanner_RS/astar.py
MADRLmine/Hybrid_A_starPlanner_RS/draw.py
MADRLmine/Hybrid_A_starPlanner_RS/hybrid_astar.py
MADRLmine/Hybrid_A_starPlanner_RS/reeds_shepp.py
MADRLmine/VehicleModel_dll/VehicleModel.py
MADRLmine/VehicleModel_dll/VehicleModelPython.dll
MADRLmine/VehicleModel_dll/__init__.py
MADRLmine/VehicleModel_dll/libcombined.so
MADRLmine/common/__init__.py
MADRLmine/common/kdtree.py
MADRLmine/common/utils.py
MADRLmine/dynamic_scenes/__init__.py
MADRLmine/dynamic_scenes/controller.py
MADRLmine/dynamic_scenes/env.py
MADRLmine/dynamic_scenes/kinetics_model.py
MADRLmine/dynamic_scenes/lookup.py
MADRLmine/dynamic_scenes/observation.py
MADRLmine/dynamic_scenes/recorder.py
MADRLmine/dynamic_scenes/scenarioOrganizer1.py
MADRLmine/dynamic_scenes/slope.py
MADRLmine/dynamic_scenes/socket_module.py
MADRLmine/dynamic_scenes/visualizer.py
MADRLmine/map_expansion/__init__.py
MADRLmine/map_expansion/bit_map.py
MADRLmine/map_expansion/map_api.py
MADRLmine/map_expansion/view_global_map.py
MADRLmine/setup/__init__.py
MADRLmine-0.0.21.dist-info/METADATA
MADRLmine-0.0.21.dist-info/WHEEL
MADRLmine-0.0.21.dist-info/top_level.txt
MADRLmine-0.0.21.dist-info/RECORD
