Metadata-Version: 2.1
Name: MADRLmine
Version: 0.0.21
Summary: A small example package
Home-page: https://github.com/kw-zheng/MADRLMine_pip
Author: kw-zheng
Author-email: kw-zheng@sjtu.edu.cn
Classifier: Programming Language :: Python :: 3
Classifier: License :: OSI Approved :: MIT License
Classifier: Operating System :: OS Independent
Requires-Python: >=3.6
Requires-Dist: pyautogui
Requires-Dist: Django>=1.11
